[{"User":"raniejogos","Address":"0x000002","Note":"Scene (16-bit)\r\n0x9e24=How to Play\r\n0x9f84=Player Select"},{"User":"raniejogos","Address":"0x000403","Note":"P1 - Moves (8-bit)\r\n\r\n[Terry]\r\n0x25 and 0x32 = Power Geyser\r\n0x26 ... 0x28 and 0x32 = Triple Geyser\r\n\r\n[Andy]\r\n0x3f, 0x40 and 0x7d = Choreppa Dan\r\n0x41 and 0x7d = Zan Ei Reppa\r\n\r\n[Joe]\r\n0x52 = Screw Upper\r\n0x55 = Slide Screw\r\n\r\n[Mai]\r\n0x64, 0x65 and 0x7d = Super Deadly Ninja Bees\r\n0x68, 0x69 and 0x7d = Leotard Ninja Bees\r\n\r\n[Geese]\r\n0x82 = Raging Storm\r\n0x85, 0x86 = Thunderbreaker\r\n0x7d ... 0x7f = Deadly Rave\r\n\r\n[Sokaku]\r\n0xbc, 0xbd = Ikazuchi\r\n0xbf = Thundergod Exhalation\r\n\r\n[Bob]\r\n0xd0 ... 0xd3 and 0x7d = Dangerous Wolf\r\n0xd4 and 0x7d = Madly Spinning Wolf\r\n\r\n[Hon]\r\n0xe5, 0xe6 and 0x7d = Exploding Goro\r\n0xe8, 0xe9 = Candenza Storm\r\n\r\n[Mary]\r\n0x09 ... 0x0b = M. Typhoon\r\n0x0f, 0x10 = M. Diving Smasher\r\n\r\n[Franco]\r\n0x1d, 0x1e and 0x7d = Final Omega Shot\r\n0x1f and 0x7e = Armageddon Buster (1st part)\r\n0x20 ... 0x24 and 0x7e= Armageddon Buster (2nd part)\r\n\r\n[Yamazaki]\r\n 0x34, 0x35 and 0x7e = Guillotine\r\n0x37 ... 0x3c = Driller\r\n\r\n[Jin Chonshu]\r\n0x4c, 0x4d = Emperor Rohjin Slash\r\n0x50 = Emperor Doomed Slash\r\n\r\n[Jin Chonrei]\r\n0x5b = Emperor Doomed Slash\r\n0x5d = Emperor Ryusei Slash\r\n\r\n[Duck]\r\n0x69, 0x6a = Break Spiral\r\n0x6d, 0x6e = Duck Dance\r\n0x6f, 0x70 = Break Hurricane\r\n0x72 = Dancing Caliber\r\n0x73, 0x74 = Rolling Punisher\r\n0x75, 0x76 = Diving Punisher\r\n\r\n[Kim]\r\n0x7f ... 0x80 = Phoenix Fandango Kick\r\n0x84, 0x85 = Chinese Phoenix Kick\r\n\r\n[Joe]\r\n0x39 and 0x9a = Super Fire Wheel\r\n0x9c, 0x9d, 0x32 and 0x7d = Red Lotus Killer Cudgel"},{"User":"raniejogos","Address":"0x000410","Note":"P1 - Character (8-bit)"},{"User":"Salsa","Address":"0x000411","Note":"P1 Character"},{"User":"Salsa","Address":"0x000488","Note":"P1 Health"},{"User":"raniejogos","Address":"0x0004b5","Note":"P1 - Moves (8-bit)\r\n\r\n[Terry]\r\n0xb8 = Power Geyser\r\n0xc4 = Triple Geyser\r\n\r\n[Andy]\r\n0xb8, 0xb9 = Choreppa Dan\r\n0xc4 ... 0xc6 = Zan Ei Reppa\r\n\r\n[Joe]\r\n0xb8 = Screw Upper\r\n0xc4 = Slide Screw\r\n\r\n[Mai]\r\n0xb8 ... 0xba = Super Deadly Ninja Bees\r\n0xc4, 0xc5 = Leotard Ninja Bees\r\n\r\n[Geese]\r\n0xb8 = Raging Storm\r\n0xc4 = Thunderbreaker\r\n0xa0 ... 0xa8 = Deadly Rave\r\n\r\n[Sokaku]\r\n0xb8 = Ikazuchi\r\n0xc4 = Thundergod Exhalation\r\n\r\n[Bob]\r\n0xb8 ... 0xbb = Dangerous Wolf\r\n0xc4, 0xc5  = Madly Spinning Wolf\r\n\r\n[Hon]\r\n0xb8 = Exploding Goro\r\n0xc5 = Candenza Storm\r\n\r\n[Mary]\r\n0xb8 = M. Typhoon\r\n0xc4 = M. Diving Smasher\r\n\r\n[Franco]\r\n0xb8 = Final Omega Shot\r\n0xc4, 0xc5 = Armageddon Buster (1st part)\r\n0xc6 ... 0xcf = Armageddon Buster (2nd part)\r\n\r\n[Yamazaki]\r\n0xb8 = Guillotine\r\n0xc4 = Driller\r\n\r\n[Jin Chonshu]\r\n0xb8 = Emperor Rohjin Slash\r\n0xc4 = Emperor Doomed Slash\r\n\r\n[Jin Chonrei]\r\n0xb8 = Emperor Doomed Slash\r\n0xc4 = Emperor Ryusei Slash\r\n\r\n[Duck]\r\n0xb8 = Break Spiral\r\n0xc4 = Duck Dance\r\n0x9a ... 0x9d = Break Hurricane\r\n0xa2= Dancing Caliber\r\n0xac = Diving Punisher\r\n0xa6 = Rolling Punisher\r\n\r\n[Kim]\r\n0xb8 = Phoenix Fandango Kick\t\r\n0xc5 = Chinese Phoenix Kick\r\n\r\n[Joe]\r\n0xb8 = Super Fire Wheel\r\n0xc4 = Red Lotus Killer Cudgel"},{"User":"Salsa","Address":"0x0004bb","Note":"P1 Special bar"},{"User":"Salsa","Address":"0x000510","Note":"P2 character"},{"User":"raniejogos","Address":"0x00055b","Note":"Bit4=P2 Out of Bounds"},{"User":"Salsa","Address":"0x000588","Note":"P2 Health"},{"User":"raniejogos","Address":"0x0005cf","Note":"Bit2=P2 Out of Bounds"},{"User":"raniejogos","Address":"0x000930","Note":""},{"User":"raniejogos","Address":"0x000b50","Note":"Camera - X-axis (8-bit)\r\n0x1e=Center"},{"User":"raniejogos","Address":"0x000b52","Note":"Camera - X-axis (8-bit)\r\n0x1e=Center"},{"User":"raniejogos","Address":"0x000c50","Note":"Camera - X-axis (8-bit)\r\n0x1a=Center"},{"User":"raniejogos","Address":"0x000c52","Note":"Camera - X-axis (8-bit)\r\n0x1a=Center"},{"User":"raniejogos","Address":"0x001582","Note":"COM vs 2P - Character Select"},{"User":"raniejogos","Address":"0x002782","Note":"1P - Character Select"},{"User":"raniejogos","Address":"0x002784","Note":"COM vs 1P - Character Select"},{"User":"raniejogos","Address":"0x0027a0","Note":"P2 - Character (8-bit)"},{"User":"raniejogos","Address":"0x002882","Note":""},{"User":"raniejogos","Address":"0x003c82","Note":""},{"User":"raniejogos","Address":"0x004120","Note":""},{"User":"raniejogos","Address":"0x006a1f","Note":"0x05=Out of Bounds"},{"User":"raniejogos","Address":"0x006a23","Note":"Throwing the opponent on the screen perspective\r\n0x05 -> 0x04"},{"User":"raniejogos","Address":"0x006a24","Note":"P1 - Character (8-bit)\r\n0x01=Terry\r\n0x02=Andy\r\n0x03=Joe\r\n0x04=Mai\r\n0x05=Geese Howard\r\n0x06=Sokaku Mochizuki\r\n0x07=Bob Wilson\r\n0x08=Hon Fu\r\n0x09=Blue Mary\r\n0x0a=Franco Bash\r\n0x0b=Ryuji Yamazaki\r\n0x0c=Jin Chonshu\r\n0x0d=Jin Chonrei\r\n0x0e=Duck King\r\n0x0f=Kim Kaphwan\r\n0x10=Billy Kane"},{"User":"raniejogos","Address":"0x006a26","Note":"P2 - Character (8-bit)"},{"User":"raniejogos","Address":"0x006a28","Note":"P1 - Character (8-bit)"},{"User":"raniejogos","Address":"0x006a2e","Note":"Stage (8-bit)\r\n0x01=Sound Beach\r\n0x02=West Subway\r\n0x03=East Side Park\r\n0x04=Southtown Bridge\r\n0x05=Geese Tower"},{"User":"raniejogos","Address":"0x006a30","Note":"Alternative Stage (8-bit)\r\n0x00=1st\r\n0x01=2nd\r\n0x02=3rd"},{"User":"Salsa","Address":"0x006a36","Note":"Fight"},{"User":"raniejogos","Address":"0x006a3e","Note":"P2 - Character (8-bit)"},{"User":"Salsa","Address":"0x006a76","Note":"P2 won rounds"},{"User":"Salsa","Address":"0x006a77","Note":"P1 won rounds"},{"User":"raniejogos","Address":"0x006a8a","Note":""},{"User":"Salsa","Address":"0x006aa9","Note":"Round Timer"},{"User":"raniejogos","Address":"0x006abb","Note":"Round Grade (8-bit)"},{"User":"raniejogos","Address":"0x006ae0","Note":"Alternative Stage - Out of Bounds (8-bit)\r\n0xFF = Right side destroyed"},{"User":"raniejogos","Address":"0x006ae1","Note":"Alternative Stage - Out of Bounds (8-bit)\r\n0xFF = Left side destroyed"},{"User":"raniejogos","Address":"0x006ae2","Note":"Alternative Stage - Left Side (8-bit)\r\n0x00=Rail Trail\r\n0x01=Train\r\n0x01->0x02=Train Moving"},{"User":"raniejogos","Address":"0x006ae4","Note":"Alternative Stage - Right Side (8-bit)\r\n0x00=Rail Trail\r\n0x01=Train\r\n0x01->0x02=Train Moving"},{"User":"raniejogos","Address":"0x006ae6","Note":"Out of Bounds (Bit0)\r\nSound Beach - Seafood cafe signboard (Left)"},{"User":"raniejogos","Address":"0x006ae8","Note":"Out of Bounds (Bit0)\r\nSound Beach - Kiosk (Right)"},{"User":"raniejogos","Address":"0x006aea","Note":"P2 - Out of Bounds (8-bit)\r\n0xFF"},{"User":"raniejogos","Address":"0x006aeb","Note":"P1 - Out of Bounds (8-bit)\r\n0xFF"},{"User":"raniejogos","Address":"0x006aee","Note":"0x01=Out of Bounds"},{"User":"Salsa","Address":"0x009a0f","Note":"P1 Hits"},{"User":"raniejogos","Address":"0x00a438","Note":"P2 - Taking damage (8-bit)"},{"User":"Salsa","Address":"0x00e00a","Note":"P1 Score 00XX0000"},{"User":"Salsa","Address":"0x00e00b","Note":"P1 Score XX000000"},{"User":"Salsa","Address":"0x00e00c","Note":"P1 Score 000000XX"},{"User":"Salsa","Address":"0x00e00d","Note":"P1 Score 0000XX00"},{"User":"Salsa","Address":"0x00fd89","Note":"Soft Dip Setup - play itme"},{"User":"Salsa","Address":"0x00fd8a","Note":"Soft Dip Setup - toggle demo sound"},{"User":"Salsa","Address":"0x00fd8b","Note":"Soft Dip Setup - continue"},{"User":"Salsa","Address":"0x00fd8c","Note":"Soft Dip Setup - difficullty\r\n00=1(easiest)\r\n03=4(default)\r\n07=8(hardest)"},{"User":"Salsa","Address":"0x00fd8d","Note":"Soft Dip Setup - toggle how to play"},{"User":"Salsa","Address":"0x00fd8e","Note":"Soft Dip Setup - toggle 1credit vs"},{"User":"Salsa","Address":"0x00fd8f","Note":"Soft Dip Setup - credit indicator"},{"User":"Salsa","Address":"0x00fd90","Note":"Soft Dip Setup - level indicator"},{"User":"Salsa","Address":"0x00fd92","Note":"Soft Dip Setup - language"},{"User":"Salsa","Address":"0x00fd93","Note":"Soft Dip Setup - blood color"},{"User":"Salsa","Address":"0x00fdb6","Note":"P2 Status\r\n00=inactive\r\n01=active\r\n02=continue\r\n03=game over"},{"User":"Salsa","Address":"0x00fdb7","Note":"P1 Status\r\n00=inactive\r\n01=active\r\n02=continue\r\n03=game over"}]